.gitignore
CHANGES.rst
CONTRIBUTORS.rst
MANIFEST.in
README.rst
buildout.cfg
setup.cfg
setup.py
docs/INSTALL.txt
docs/LICENSE.EUPL
docs/LICENSE.GPL
docs/LICENSE.txt
slc/__init__.py
slc.publications.egg-info/PKG-INFO
slc.publications.egg-info/SOURCES.txt
slc.publications.egg-info/dependency_links.txt
slc.publications.egg-info/entry_points.txt
slc.publications.egg-info/namespace_packages.txt
slc.publications.egg-info/not-zip-safe
slc.publications.egg-info/requires.txt
slc.publications.egg-info/top_level.txt
slc/publications/TODO.txt
slc/publications/__init__.py
slc/publications/config.py
slc/publications/configure.zcml
slc/publications/descriptors.py
slc/publications/displays.py
slc/publications/interfaces.py
slc/publications/linguaplone_addTranslation_patch.py
slc/publications/missing_18n_labels.py
slc/publications/overrides.zcml
slc/publications/profiles.zcml
slc/publications/refresh.txt
slc/publications/setuphandlers.py
slc/publications/skins.zcml
slc/publications/utils.py
slc/publications/version.txt
slc/publications/adapter/__init__.py
slc/publications/adapter/configure.zcml
slc/publications/adapter/events.py
slc/publications/adapter/publication.py
slc/publications/adapter/xliff.py
slc/publications/browser/__init__.py
slc/publications/browser/configure.zcml
slc/publications/browser/media.py
slc/publications/browser/publication.py
slc/publications/browser/publications.py
slc/publications/browser/publications_by_subject.py
slc/publications/browser/support.py
slc/publications/browser/jbot/plone.portlet.collection.collection.pt
slc/publications/browser/resources/buttonSchwusch.png
slc/publications/browser/resources/iconPDF.png
slc/publications/browser/resources/jquery.qtip-1.0.0-rc3.min.js
slc/publications/browser/resources/loader.gif
slc/publications/browser/resources/publications.css
slc/publications/browser/resources/publications.js
slc/publications/browser/templates/estimate_template.pt
slc/publications/browser/templates/publication-container.pt
slc/publications/browser/templates/publication-edit.pt
slc/publications/browser/templates/publication.pt
slc/publications/browser/templates/publication_macros.pt
slc/publications/browser/templates/publication_relatedItems.pt
slc/publications/browser/templates/publications.pt
slc/publications/browser/templates/publications_by_subject.pt
