Metadata-Version: 1.1
Name: slc.publications
Version: 4.7.6
Summary: A content type to store and parse pdf publications
Home-page: http://plone.org/products/slc.publications
Author: Syslab.com GmbH
Author-email: info@syslab.com
License: GPL + EUPL
Keywords: plone content publications pdf parse metadata
Platform: UNKNOWN
Classifier: Framework :: Plone
Classifier: Framework :: Zope2
Classifier: Framework :: Zope3
Classifier: Programming Language :: Python
Classifier: Topic :: Software Development :: Libraries :: Python Modules
Classifier: License :: OSI Approved :: GNU General Public License (GPL)
Classifier: License :: OSI Approved :: European Union Public Licence 1.1 (EUPL 1.1)
